ku/__init__.py
ku/ku.py
ku/ku_dot.py
ku/ku_img_found.py
ku-0.0.1.dist-info/LICENSE
ku-0.0.1.dist-info/METADATA
ku-0.0.1.dist-info/WHEEL
ku-0.0.1.dist-info/top_level.txt
ku-0.0.1.dist-info/RECORD
