Metadata-Version: 2.1
Name: ku
Version: 0.0.1
Summary: A serials of tools for iOS develper
Home-page: https://github.com/pypa/sampleproject
Author: Lefex
Author-email: wsyxyxs@126.com
License: UNKNOWN
Platform: UNKNOWN
Classifier: Programming Language :: Python :: 3
Classifier: License :: OSI Approved :: MIT License
Classifier: Operating System :: OS Independent
